semantic_versioning_utility-0.3.6.dist-info/licenses/LICENSE
versioning_tool/__init__.py
versioning_tool/changelog.py
versioning_tool/config.py
versioning_tool/core.py
versioning_tool/graph.py
versioning_tool/rules.py
versioning_tool/version_manager.py
semantic_versioning_utility-0.3.6.dist-info/METADATA
semantic_versioning_utility-0.3.6.dist-info/WHEEL
semantic_versioning_utility-0.3.6.dist-info/entry_points.txt
semantic_versioning_utility-0.3.6.dist-info/top_level.txt
semantic_versioning_utility-0.3.6.dist-info/RECORD
