Metadata-Version: 2.4
Name: semantic-versioning-utility
Version: 0.3.6
Summary: Automatic versioning and changelog generation utility.
Author: Tenbatsu24
License:                                  Apache License
Project-URL: Homepage, https://github.com/Tenbatsu24/versioning-utility
Project-URL: Documentation, https://github.com/Tenbatsu24/versioning-utility#readme
Project-URL: Usage, https://github.com/Tenbatsu24/versioning-utility/blob/main/USAGE.md
Project-URL: Workflow, https://github.com/Tenbatsu24/versioning-utility/blob/main/RELEASE_WORKFLOW.md
Classifier: Programming Language :: Python :: 3.11
Classifier: License :: OSI Approved :: Apache Software License
Classifier: Development Status :: 4 - Beta
Classifier: Intended Audience :: Developers
Classifier: Topic :: Software Development :: Version Control
Classifier: Topic :: Software Development :: Libraries :: Python Modules
Classifier: Operating System :: OS Independent
Requires-Python: >=3.11
License-File: LICENSE
Requires-Dist: pyyaml>=6.0
Requires-Dist: jinja2>=3.1
Dynamic: license-file
